story_maker/__init__.py
story_maker/blessing_pro.py
story_maker/main_frame.py
story_maker/stories/BlessingPro/BlessingPro1.zip
story_maker/stories/BlessingPro/BlessingPro2.zip
story_maker/stories/BlessingPro/BlessingPro3.zip
story_maker/stories/BlessingPro/BlessingPro4.zip
story_maker/story_archive/__init__.py
story_maker/story_archive/choices.py
story_maker/story_archive/story_archive.py
story_maker/story_archive/story_data.py
story_maker/story_archive/story_load.py
story_maker/story_structure/__init__.py
story_maker/story_structure/story_beginning.py
story_maker/story_structure/story_multiple_choices.py
story_maker/story_structure/story_multiple_stories.py
story_maker/story_structure/story_save_delete_button.py
story_maker/story_structure/story_selection.py
storymaker_karjakak-1.0.8.dist-info/licenses/LICENSE
storymaker_karjakak-1.0.8.dist-info/METADATA
storymaker_karjakak-1.0.8.dist-info/WHEEL
storymaker_karjakak-1.0.8.dist-info/entry_points.txt
storymaker_karjakak-1.0.8.dist-info/top_level.txt
storymaker_karjakak-1.0.8.dist-info/RECORD
