Metadata-Version: 2.4
Name: StoryMaker-karjakak
Version: 1.0.8
Summary: Story Maker for devotion and blessing for others.
Author: karjakak
Author-email: kakkarja.github@gmail.com
License: # BSD 3-Clause License
Project-URL: Homepage, https://github.com/kakkarja/Story_Maker
Keywords: Story Maker,Interactive Story,Devotion,Story Reader,Stories
Classifier: Environment :: Win32 (MS Windows)
Classifier: Environment :: MacOS X
Classifier: Intended Audience :: End Users/Desktop
Classifier: Programming Language :: Python :: 3.10
Requires-Python: >=3.10
License-File: LICENSE
Dynamic: license-file
